doge/__init__.py
doge/__main__.py
doge/core.py
doge/wow.py
doge/static/doge-earth.txt
doge/static/doge-easter.txt
doge/static/doge-halloween.txt
doge/static/doge-kabosu.txt
doge/static/doge-moon.txt
doge/static/doge-small.txt
doge/static/doge-thanksgiving.txt
doge/static/doge-valentine.txt
doge/static/doge-xmas.txt
doge/static/doge.txt
doge-3.9.0.dist-info/METADATA
doge-3.9.0.dist-info/WHEEL
doge-3.9.0.dist-info/entry_points.txt
doge-3.9.0.dist-info/licenses/LICENSE
doge-3.9.0.dist-info/RECORD
