Metadata-Version: 2.4
Name: doge
Version: 3.9.0
Summary: wow very terminal doge
Project-URL: Homepage, https://github.com/Olivia5k/doge
Author-email: Olivia Thiderman <olivia@thiderman.org>
License-Expression: MIT
License-File: LICENSE
Classifier: Development Status :: 5 - Production/Stable
Classifier: Environment :: Console
Classifier: License :: OSI Approved :: MIT License
Classifier: Operating System :: Unix
Classifier: Programming Language :: Python :: 3
Classifier: Programming Language :: Python :: 3.9
Classifier: Programming Language :: Python :: 3.10
Classifier: Programming Language :: Python :: 3.11
Classifier: Programming Language :: Python :: 3.12
Classifier: Programming Language :: Python :: 3.13
Requires-Python: >=3.9
Requires-Dist: fullmoon>=1.0.2
Requires-Dist: python-dateutil>=2.8.2
